CHANGELOG
LICENSE
MANIFEST.in
setup.py
bin/launchpadstats
bin/launchpadstats-all
launchpadstats/__init__.py
launchpadstats/configuration.py
launchpadstats/stackalytics.py
launchpadstats/table.py
launchpadstats.egg-info/PKG-INFO
launchpadstats.egg-info/SOURCES.txt
launchpadstats.egg-info/dependency_links.txt
launchpadstats.egg-info/requires.txt
launchpadstats.egg-info/top_level.txt