Metadata-Version: 1.0
Name: launchpadstats
Version: 0.1.3
Summary: Get data from Stackalytics trough the CLI.
Home-page: https://github.com/mkollaro/launchpadstats
Author: Martina Kollarova
Author-email: mkollaro@gmail.com
License: Apache License, Version 2.0
Platform: UNKNOWN
